xtnkk_tools/MongoDB.py
xtnkk_tools/__init__.py
xtnkk_tools/tools.py
xtnkk_tools/tools_time.py
xtnkk_tools/update.py
xtnkk_tools/db/MongoDB.py
xtnkk_tools/db/__init__.py
xtnkk_tools_pro/__init__.py
xtnkk_tools_pro/tools.py
xtnkk_tools_pro/tools_time.py
xtnkk_tools_pro/db/MongoDB.py
xtnkk_tools_pro/db/RedisDB.py
xtnkk_tools_pro/db/__init__.py
xtnkk_tools_pro-1.0.0.0.0.dist-info/LICENSE
xtnkk_tools_pro-1.0.0.0.0.dist-info/METADATA
xtnkk_tools_pro-1.0.0.0.0.dist-info/WHEEL
xtnkk_tools_pro-1.0.0.0.0.dist-info/top_level.txt
xtnkk_tools_pro-1.0.0.0.0.dist-info/RECORD
