Metadata-Version: 2.1
Name: xtnkk-tools-pro
Version: 1.0.0.0.0
Summary: xtn 开发工具
Author: xtn
Author-email: czw011122@163.com
Classifier: Programming Language :: Python :: 3
Requires-Python: >=3
License-File: LICENSE
Requires-Dist: pymongo
Requires-Dist: redis
